<?xml version="1.0" encoding="UTF-8"?><record_update>
    <sys_choice action="INSERT_OR_UPDATE" field="state" table="x_snc_loan_rq_loaner_request" version="3">
        <sys_choice_set action="INSERT_OR_UPDATE">
            <element>state</element>
            <name>x_snc_loan_rq_loaner_request</name>
            <sys_class_name>sys_choice_set</sys_class_name>
            <sys_created_by>admin</sys_created_by>
            <sys_created_on>2022-06-16 16:55:55</sys_created_on>
            <sys_id>67642ab687cc9150858e0fe5dabb3559</sys_id>
            <sys_mod_count>0</sys_mod_count>
            <sys_name>state</sys_name>
            <sys_package display_value="Loaner Request" source="x_snc_loan_rq">034cac3e87489150858e0fe5dabb357c</sys_package>
            <sys_policy/>
            <sys_scope display_value="Loaner Request">034cac3e87489150858e0fe5dabb357c</sys_scope>
            <sys_update_name>sys_choice_x_snc_loan_rq_loaner_request_state</sys_update_name>
            <sys_updated_by>admin</sys_updated_by>
            <sys_updated_on>2022-06-16 16:55:55</sys_updated_on>
        </sys_choice_set>
        <sys_choice action="INSERT_OR_UPDATE">
            <dependent_value/>
            <element>state</element>
            <hint/>
            <inactive>false</inactive>
            <label>Request</label>
            <language>en</language>
            <name>x_snc_loan_rq_loaner_request</name>
            <sequence>0</sequence>
            <synonyms/>
            <sys_created_by>admin</sys_created_by>
            <sys_created_on>2022-06-16 16:55:55</sys_created_on>
            <sys_domain>global</sys_domain>
            <sys_domain_path>/</sys_domain_path>
            <sys_id>23642ab687cc9150858e0fe5dabb3559</sys_id>
            <sys_mod_count>0</sys_mod_count>
            <sys_updated_by>admin</sys_updated_by>
            <sys_updated_on>2022-06-16 16:55:55</sys_updated_on>
            <value>13</value>
        </sys_choice>
        <sys_choice action="INSERT_OR_UPDATE">
            <dependent_value/>
            <element>state</element>
            <hint/>
            <inactive>false</inactive>
            <label>Reserved</label>
            <language>en</language>
            <name>x_snc_loan_rq_loaner_request</name>
            <sequence>1</sequence>
            <synonyms/>
            <sys_created_by>admin</sys_created_by>
            <sys_created_on>2022-06-16 16:55:55</sys_created_on>
            <sys_domain>global</sys_domain>
            <sys_domain_path>/</sys_domain_path>
            <sys_id>ef642ab687cc9150858e0fe5dabb355b</sys_id>
            <sys_mod_count>0</sys_mod_count>
            <sys_updated_by>admin</sys_updated_by>
            <sys_updated_on>2022-06-16 16:55:55</sys_updated_on>
            <value>14</value>
        </sys_choice>
        <sys_choice action="INSERT_OR_UPDATE">
            <dependent_value/>
            <element>state</element>
            <hint/>
            <inactive>false</inactive>
            <label>Deployment Prep</label>
            <language>en</language>
            <name>x_snc_loan_rq_loaner_request</name>
            <sequence>2</sequence>
            <synonyms/>
            <sys_created_by>admin</sys_created_by>
            <sys_created_on>2022-06-16 16:55:55</sys_created_on>
            <sys_domain>global</sys_domain>
            <sys_domain_path>/</sys_domain_path>
            <sys_id>a3642ab687cc9150858e0fe5dabb355e</sys_id>
            <sys_mod_count>0</sys_mod_count>
            <sys_updated_by>admin</sys_updated_by>
            <sys_updated_on>2022-06-16 16:55:55</sys_updated_on>
            <value>15</value>
        </sys_choice>
        <sys_choice action="INSERT_OR_UPDATE">
            <dependent_value/>
            <element>state</element>
            <hint/>
            <inactive>false</inactive>
            <label>Ready for pick up</label>
            <language>en</language>
            <name>x_snc_loan_rq_loaner_request</name>
            <sequence>3</sequence>
            <synonyms/>
            <sys_created_by>admin</sys_created_by>
            <sys_created_on>2022-06-16 16:55:55</sys_created_on>
            <sys_domain>global</sys_domain>
            <sys_domain_path>/</sys_domain_path>
            <sys_id>67642ab687cc9150858e0fe5dabb3560</sys_id>
            <sys_mod_count>0</sys_mod_count>
            <sys_updated_by>admin</sys_updated_by>
            <sys_updated_on>2022-06-16 16:55:55</sys_updated_on>
            <value>16</value>
        </sys_choice>
        <sys_choice action="INSERT_OR_UPDATE">
            <dependent_value/>
            <element>state</element>
            <hint/>
            <inactive>false</inactive>
            <label>Checked Out</label>
            <language>en</language>
            <name>x_snc_loan_rq_loaner_request</name>
            <sequence>4</sequence>
            <synonyms/>
            <sys_created_by>admin</sys_created_by>
            <sys_created_on>2022-06-16 16:55:55</sys_created_on>
            <sys_domain>global</sys_domain>
            <sys_domain_path>/</sys_domain_path>
            <sys_id>2b642ab687cc9150858e0fe5dabb3562</sys_id>
            <sys_mod_count>0</sys_mod_count>
            <sys_updated_by>admin</sys_updated_by>
            <sys_updated_on>2022-06-16 16:55:55</sys_updated_on>
            <value>17</value>
        </sys_choice>
        <sys_choice action="INSERT_OR_UPDATE">
            <dependent_value/>
            <element>state</element>
            <hint/>
            <inactive>false</inactive>
            <label>Post Deployment</label>
            <language>en</language>
            <name>x_snc_loan_rq_loaner_request</name>
            <sequence>5</sequence>
            <synonyms/>
            <sys_created_by>admin</sys_created_by>
            <sys_created_on>2022-06-16 16:55:55</sys_created_on>
            <sys_domain>global</sys_domain>
            <sys_domain_path>/</sys_domain_path>
            <sys_id>eb642ab687cc9150858e0fe5dabb3564</sys_id>
            <sys_mod_count>0</sys_mod_count>
            <sys_updated_by>admin</sys_updated_by>
            <sys_updated_on>2022-06-16 16:55:55</sys_updated_on>
            <value>18</value>
        </sys_choice>
        <sys_choice action="INSERT_OR_UPDATE">
            <dependent_value/>
            <element>state</element>
            <hint/>
            <inactive>false</inactive>
            <label>Closed Complete</label>
            <language>en</language>
            <name>x_snc_loan_rq_loaner_request</name>
            <sequence>6</sequence>
            <synonyms/>
            <sys_created_by>admin</sys_created_by>
            <sys_created_on>2022-06-16 16:55:55</sys_created_on>
            <sys_domain>global</sys_domain>
            <sys_domain_path>/</sys_domain_path>
            <sys_id>af642ab687cc9150858e0fe5dabb3566</sys_id>
            <sys_mod_count>0</sys_mod_count>
            <sys_updated_by>admin</sys_updated_by>
            <sys_updated_on>2022-06-16 16:55:55</sys_updated_on>
            <value>3</value>
        </sys_choice>
    </sys_choice>
</record_update>
